uuid_visualizer/__init__.py
uuid_visualizer/main.py
uuid_visualizer/palettes.py
uuid_visualizer/shapes.py
uuid_visualizer-1.0.0.dist-info/licenses/LICENSE
uuid_visualizer-1.0.0.dist-info/METADATA
uuid_visualizer-1.0.0.dist-info/WHEEL
uuid_visualizer-1.0.0.dist-info/top_level.txt
uuid_visualizer-1.0.0.dist-info/RECORD
