Metadata-Version: 2.4
Name: uuid-visualizer
Version: 1.0.0
Summary: Generate stylized visual keys based on UUID input.
Author: Aurora Rosabella
Author-email: Aurora Rosabella <auracrimsonrose@gmail.com>
License: MIT
Project-URL: Homepage, https://github.com/auroracrimsonrose/uuid-visualizer
Project-URL: Repository, https://github.com/auroracrimsonrose/uuid-visualizer
Requires-Python: >=3.6
License-File: LICENSE
Requires-Dist: Pillow
Dynamic: author
Dynamic: license-file
Dynamic: requires-python
